Metadata-Version: 2.1
Name: hn-test-num
Version: 0.1
Summary: sum
Home-page: http://github.com/tongling/clinicaltrial
Author: wangxing
Author-email: 470755846@qq.com
License: MIT
Platform: UNKNOWN
